{
	"plots":
	{
		"VerticesEdit_qs7d22ofXN":
		{
			"_id": "VerticesEdit_qs7d22ofXN",
			"uName": "VerticesEdit_qs7d22ofXN",
			"vertices": [
				{
					"v":
					{
						"x": -896.21038818359375,
						"y": -1217.3314208984375,
						"z": 52.5673828125
					}
				},
				{
					"v":
					{
						"x": -753.775146484375,
						"y": -947.18695068359375,
						"z": 69.19970703125
					}
				},
				{
					"v":
					{
						"x": -509.60076904296875,
						"y": -727.302001953125,
						"z": 45.0904541015625
					}
				},
				{
					"v":
					{
						"x": -214.55662536621094,
						"y": -494.85226440429688,
						"z": 11.06280517578125
					}
				},
				{
					"v":
					{
						"x": -87.382209777832031,
						"y": -576.5238037109375,
						"z": 14.5723876953125
					}
				},
				{
					"v":
					{
						"x": 44.878787994384766,
						"y": -563.95892333984375,
						"z": 30.2891845703125
					}
				},
				{
					"v":
					{
						"x": 172.05322265625,
						"y": -457.1575927734375,
						"z": 59.128662109375
					}
				},
				{
					"v":
					{
						"x": 283.966552734375,
						"y": -450.87515258789062,
						"z": 32.2728271484375
					}
				},
				{
					"v":
					{
						"x": 329.749267578125,
						"y": -356.63882446289062,
						"z": 27.2373046875
					}
				},
				{
					"v":
					{
						"x": 324.66213989257812,
						"y": -218.42538452148438,
						"z": 29.3736572265625
					}
				},
				{
					"v":
					{
						"x": 492.53213500976562,
						"y": -23.670127868652344,
						"z": 36.0875244140625
					}
				},
				{
					"v":
					{
						"x": 563.7496337890625,
						"y": 428.6646728515625,
						"z": 28.9158935546875
					}
				},
				{
					"v":
					{
						"x": 594.27154541015625,
						"y": 554.313232421875,
						"z": 23.117431640625
					}
				},
				{
					"v":
					{
						"x": 548.48883056640625,
						"y": 723.93865966796875,
						"z": 21.59149169921875
					}
				},
				{
					"v":
					{
						"x": 289.05340576171875,
						"y": 1220.2506103515625,
						"z": 33.6461181640625
					}
				},
				{
					"v":
					{
						"x": -845.34075927734375,
						"y": 1232.8155517578125,
						"z": 0.0762939453125
					}
				},
				{
					"v":
					{
						"x": -957.254150390625,
						"y": 1000.3655395507812,
						"z": 7.09539794921875
					}
				},
				{
					"v":
					{
						"x": -967.42779541015625,
						"y": 635.98486328125,
						"z": 33.0357666015625
					}
				},
				{
					"v":
					{
						"x": -987.7757568359375,
						"y": 535.46588134765625,
						"z": 44.6326904296875
					}
				},
				{
					"v":
					{
						"x": -1109.863037109375,
						"y": 648.54974365234375,
						"z": 6.79022216796875
					}
				},
				{
					"v":
					{
						"x": -1109.863037109375,
						"y": 390.97018432617188,
						"z": 78.3551025390625
					}
				},
				{
					"v":
					{
						"x": -1226.86328125,
						"y": 485.20651245117188,
						"z": 18.23455810546875
					}
				},
				{
					"v":
					{
						"x": -1237.0372314453125,
						"y": -1217.3314208984375,
						"z": 223.7735595703125
					}
				}
			],
			"posCenter":
			{
				"v":
				{
					"x": -315.63238525390625,
					"y": 26.316150665283203,
					"z": 77.1343994140625
				}
			},
			"buildPattern": "",
			"averagePlotDistance": 100,
			"squareMeters": 3158827.25,
			"parentPlotUName": "",
			"childPlotUNames": [],
			"verticesBuffer": -25
		}
	}
}